flit_core/__init__.py
flit_core/_spdx_data.py
flit_core/buildapi.py
flit_core/common.py
flit_core/config.py
flit_core/sdist.py
flit_core/versionno.py
flit_core/wheel.py
flit_core/vendor/README
flit_core/vendor/__init__.py
flit_core/vendor/tomli/__init__.py
flit_core/vendor/tomli/_parser.py
flit_core/vendor/tomli/_re.py
flit_core/vendor/tomli/_types.py
flit_core/vendor/tomli/py.typed
flit_core/vendor/tomli-1.2.3.dist-info/LICENSE
flit_core/vendor/tomli-1.2.3.dist-info/METADATA
flit_core-3.11.0.dist-info/licenses/LICENSE
flit_core-3.11.0.dist-info/licenses/flit_core/vendor/tomli-1.2.3.dist-info/LICENSE
flit_core-3.11.0.dist-info/WHEEL
flit_core-3.11.0.dist-info/METADATA
flit_core-3.11.0.dist-info/RECORD
