Metadata-Version: 2.4
Name: flit_core
Version: 3.11.0
Summary: Distribution-building parts of Flit. See flit package for more information
Author-email: Thomas Kluyver & contributors <thomas@kluyver.me.uk>
Requires-Python: >=3.6
License-Expression: BSD-3-Clause
Classifier: Topic :: Software Development :: Libraries :: Python Modules
License-File: LICENSE
License-File: flit_core/vendor/tomli-1.2.3.dist-info/LICENSE
Project-URL: Documentation, https://flit.pypa.io
Project-URL: Source, https://github.com/pypa/flit
